{
  "date": "2023-12-07T01:45:36.002Z",
  "data": {
    "astro": {
      "issuePerLabel": {
        "needs triage": 4,
        "- P4: important": 26,
        "feat: i18n": 2,
        "- P3: minor bug": 59,
        "cached build": 4,
        "feat: errors": 4,
        "feat: assets": 9,
        "feat: styling": 10,
        "regression": 1,
        "feat: toolbar": 2,
        "ecosystem: external": 3,
        "pkg: astro": 1,
        "- P2: nice to have": 18,
        "pkg: vue": 2,
        "- P2: has workaround": 7,
        "feat: markdown": 2,
        "needs repro": 1,
        "feat: content collections": 9,
        "pkg: upgrade": 1,
        "feat: hmr": 3,
        "pkg: vercel": 5,
        "feat: redirects": 5,
        "ecosystem: upstream": 4,
        "feat: ssr": 8,
        "help wanted": 4,
        "pkg: rss": 1,
        "needs response": 3,
        "pkg: svelte": 1,
        "pkg: markdoc": 3,
        "pkg: node": 2,
        "pkg: react": 2,
        "feat: dev": 4,
        "feat: error pages": 4,
        "requires refactor": 7,
        "needs discussion": 4,
        "- P1: chore": 1,
        "pkg: create-astro": 1,
        "pkg: tailwind": 1,
        "feat: view transitions": 4,
        "pkg: mdx": 3,
        "feat: typescript": 1,
        "feat: add": 2,
        "pkg: integration": 2,
        "pkg: lit": 2,
        "feat: middleware": 1,
        "pkg: preact": 1,
        "pkg: solid": 5
      },
      "issueCount": 129
    },
    "docs": {
      "issuePerLabel": {
        "improve documentation": 6,
        "should this be documented?": 2,
        "tsc": 3,
        "help wanted": 5,
        "good first issue": 3,
        "add new content": 2,
        "bug": 1
      },
      "issueCount": 15
    },
    "prettier-plugin-astro": {
      "issuePerLabel": {
        "- P3: minor bug": 2,
        "- P2: has workaround": 1,
        "needs triage": 6,
        "- P4: important": 3,
        "ecosystem: compiler": 3,
        "feature": 2
      },
      "issueCount": 15
    },
    "compiler": {
      "issuePerLabel": {
        "- P4: important": 12,
        "needs triage": 22,
        "needs repro": 2,
        "- P3: minor bug": 12,
        "- P2: has workaround": 4,
        "feat: tsx": 3,
        "- P2-to-be-discussed": 1,
        "- P2: nice to have": 3,
        "- P5: urgent": 1,
        "feat: ast": 2,
        "downstream-blocker": 2,
        "help wanted": 2
      },
      "issueCount": 56
    },
    "astro-repl": {
      "issuePerLabel": {},
      "issueCount": 4
    },
    "language-tools": {
      "issuePerLabel": {
        "- P3: minor bug": 13,
        "feat: syntax": 8,
        "- P2: nice to have": 4,
        "ecosystem: upstream": 8,
        "needs investigation": 3,
        "- P2: has workaround": 8,
        "needs triage": 3,
        "- P4: important": 10,
        "ecosystem: compiler": 7,
        "feat: vue": 3,
        "feat: yarn-pnp": 2,
        "feat: svelte": 3,
        "feat: check": 1,
        "feat: pnpm": 1
      },
      "issueCount": 41
    },
    "astro.new": {
      "issuePerLabel": {},
      "issueCount": 0
    },
    "roadmap": {
      "issuePerLabel": {},
      "issueCount": 2
    },
    "withastro.github.io": {
      "issuePerLabel": {},
      "issueCount": 1
    },
    "astro.build": {
      "issuePerLabel": {},
      "issueCount": 7
    },
    "astro-playground": {
      "issuePerLabel": {},
      "issueCount": 0
    },
    ".github": {
      "issuePerLabel": {},
      "issueCount": 0
    },
    "action": {
      "issuePerLabel": {},
      "issueCount": 1
    },
    "github-pages": {
      "issuePerLabel": {},
      "issueCount": 1
    },
    "cli-kit": {
      "issuePerLabel": {},
      "issueCount": 2
    },
    "site-kit": {
      "issuePerLabel": {},
      "issueCount": 0
    },
    "blog-tutorial-demo": {
      "issuePerLabel": {},
      "issueCount": 0
    },
    "houston.astro.build": {
      "issuePerLabel": {},
      "issueCount": 2
    },
    "houston-vscode": {
      "issuePerLabel": {
        "bug": 1
      },
      "issueCount": 4
    },
    "houston-discord": {
      "issuePerLabel": {
        "bug": 1,
        "improvement": 2,
        "discord": 1,
        "feature": 3,
        "RFC": 6,
        "RFC_Implementation": 1,
        "RFC_Testing": 1
      },
      "issueCount": 8
    },
    "starlight": {
      "issuePerLabel": {
        "enhancement": 1,
        "🐛 bug": 1
      },
      "issueCount": 10
    },
    "automation": {
      "issuePerLabel": {},
      "issueCount": 0
    },
    "view-transitions-demo": {
      "issuePerLabel": {},
      "issueCount": 0
    },
    "wormhole": {
      "issuePerLabel": {},
      "issueCount": 0
    },
    "adapters": {
      "issuePerLabel": {
        "- P5: urgent": 1,
        "- P2: has workaround": 1,
        "pkg: cloudflare": 3,
        "- P2: nice to have": 3,
        "pkg: netlify": 1
      },
      "issueCount": 8
    },
    "contribute.docs.astro.build": {
      "issuePerLabel": {},
      "issueCount": 0
    }
  }
}